README.md
setup.cfg
setup.py
eis/__init__.py
eis/numbergenerator/__init__.py
eis/numbergenerator/api_client.py
eis/numbergenerator/configuration.py
eis/numbergenerator/exceptions.py
eis/numbergenerator/model_utils.py
eis/numbergenerator/rest.py
eis/numbergenerator/api/__init__.py
eis/numbergenerator/api/default_api.py
eis/numbergenerator/api/numbers_api.py
eis/numbergenerator/apis/__init__.py
eis/numbergenerator/model/__init__.py
eis/numbergenerator/model/create_number_response_class.py
eis/numbergenerator/model/entity_number_class.py
eis/numbergenerator/model/get_number_response_class.py
eis/numbergenerator/model/inline_response200.py
eis/numbergenerator/model/inline_response503.py
eis/numbergenerator/model/list_numbers_response_class.py
eis/numbergenerator/model/lookup_number_request_dto.py
eis/numbergenerator/model/reset_number_request_dto.py
eis/numbergenerator/model/update_number_response_class.py
eis/numbergenerator/models/__init__.py
eis_numbergenerator.egg-info/PKG-INFO
eis_numbergenerator.egg-info/SOURCES.txt
eis_numbergenerator.egg-info/dependency_links.txt
eis_numbergenerator.egg-info/requires.txt
eis_numbergenerator.egg-info/top_level.txt
test/test_create_number_response_class.py
test/test_default_api.py
test/test_entity_number_class.py
test/test_get_number_response_class.py
test/test_inline_response200.py
test/test_inline_response503.py
test/test_list_numbers_response_class.py
test/test_lookup_number_request_dto.py
test/test_numbers_api.py
test/test_reset_number_request_dto.py
test/test_update_number_response_class.py