Metadata-Version: 2.1
Name: eis-numbergenerator
Version: 1.1.0
Summary: EMIL Number Generator Service
Home-page: UNKNOWN
Author: Contact us
Author-email: kontakt@emil.de
License: UNKNOWN
Keywords: OpenAPI,OpenAPI-Generator,EMIL Number Generator Service
Platform: UNKNOWN
Requires-Python: >=3.6
